torch_max_mem/api.py
torch_max_mem/py.typed
torch_max_mem/version.py
torch_max_mem/__init__.py
torch_max_mem-0.1.4.dist-info/licenses/LICENSE
torch_max_mem-0.1.4.dist-info/WHEEL
torch_max_mem-0.1.4.dist-info/METADATA
torch_max_mem-0.1.4.dist-info/RECORD
