Metadata-Version: 2.4
Name: torch-max-mem
Version: 0.1.4
Summary: Maximize memory utilization with PyTorch.
Keywords: snekpack,cookiecutter,torch
Author: Max Berrendorf
Author-email: Max Berrendorf <max.berrendorf@gmail.com>
License-File: LICENSE
Classifier: Development Status :: 4 - Beta
Classifier: Environment :: Console
Classifier: Intended Audience :: Developers
Classifier: License :: OSI Approved :: MIT License
Classifier: Operating System :: OS Independent
Classifier: Framework :: Pytest
Classifier: Framework :: tox
Classifier: Framework :: Sphinx
Classifier: Programming Language :: Python
Classifier: Programming Language :: Python :: 3.9
Classifier: Programming Language :: Python :: 3.10
Classifier: Programming Language :: Python :: 3.11
Classifier: Programming Language :: Python :: 3.12
Classifier: Programming Language :: Python :: 3.13
Classifier: Programming Language :: Python :: 3 :: Only
Requires-Dist: torch>=2.0
Requires-Dist: typing-extensions
Maintainer: Max Berrendorf
Maintainer-email: Max Berrendorf <max.berrendorf@gmail.com>
Requires-Python: >=3.9
Project-URL: Bug Tracker, https://github.com/mberr/torch-max-mem/issues
Project-URL: Download, https://github.com/mberr/torch-max-mem/releases
Project-URL: Homepage, https://github.com/mberr/torch-max-mem
Project-URL: Source Code, https://github.com/mberr/torch-max-mem
